pazer_database_python/DatabaseClient.py
pazer_database_python/DatabaseHostForm.py
pazer_database_python/Executor.py
pazer_database_python/SessionClient.py
pazer_database_python/SessionHostForm.py
pazer_database_python/__init__.py
test/__init__.py
pazer_database_python-0.4.1.dist-info/LICENSE
pazer_database_python-0.4.1.dist-info/METADATA
pazer_database_python-0.4.1.dist-info/WHEEL
pazer_database_python-0.4.1.dist-info/top_level.txt
pazer_database_python-0.4.1.dist-info/RECORD
