Metadata-Version: 2.1
Name: pazer_database_python
Version: 0.4.1
Summary: Pazer Database - Python
Author: David Kim
Author-email: David Kim <woody@woody.co.kr>
Project-URL: Homepage, https://github.com/pazer-app/pazer_database_python
Project-URL: Bug Tracker, https://github.com/pazer-app/pazer_database_python/issues
Keywords: pazer,database
Classifier: Programming Language :: Python :: 3
Classifier: License :: OSI Approved :: MIT License
Classifier: Operating System :: OS Independent
Requires-Python: >=3.7
License-File: LICENSE
Requires-Dist: pazer_dataform_python>=0.4.1
Requires-Dist: pazer_logger_python>=0.4.1
Requires-Dist: pymysql>=1.1.1
Requires-Dist: redis>=5.2.1
Requires-Dist: pydantic>=2.10.4
